drf_material/__init__.py
drf_material/apps.py
drf_material/templates/rest_framework/api.html
drf_material/templates/rest_framework/filters/base.html
drf_material/templates/rest_framework/filters/ordering.html
drf_material/templates/rest_framework/filters/search.html
drf_material/templates/rest_framework/horizontal/checkbox.html
drf_material/templates/rest_framework/horizontal/checkbox_multiple.html
drf_material/templates/rest_framework/horizontal/dict_field.html
drf_material/templates/rest_framework/horizontal/fieldset.html
drf_material/templates/rest_framework/horizontal/form.html
drf_material/templates/rest_framework/horizontal/input.html
drf_material/templates/rest_framework/horizontal/list_field.html
drf_material/templates/rest_framework/horizontal/list_fieldset.html
drf_material/templates/rest_framework/horizontal/radio.html
drf_material/templates/rest_framework/horizontal/select.html
drf_material/templates/rest_framework/horizontal/select_multiple.html
drf_material/templates/rest_framework/horizontal/textarea.html
drf_material/templates/rest_framework/inline/checkbox.html
drf_material/templates/rest_framework/inline/checkbox_multiple.html
drf_material/templates/rest_framework/inline/dict_field.html
drf_material/templates/rest_framework/inline/fieldset.html
drf_material/templates/rest_framework/inline/form.html
drf_material/templates/rest_framework/inline/input.html
drf_material/templates/rest_framework/inline/list_field.html
drf_material/templates/rest_framework/inline/list_fieldset.html
drf_material/templates/rest_framework/inline/radio.html
drf_material/templates/rest_framework/inline/select.html
drf_material/templates/rest_framework/inline/select_multiple.html
drf_material/templates/rest_framework/inline/textarea.html
drf_material/templates/rest_framework/login.html
drf_material/templates/rest_framework/pagination/numbers.html
drf_material/templates/rest_framework/pagination/previous_and_next.html
drf_material/templates/rest_framework/raw_data_form.html
drf_material-0.3.4.dist-info/LICENSE
drf_material-0.3.4.dist-info/METADATA
drf_material-0.3.4.dist-info/WHEEL
drf_material-0.3.4.dist-info/RECORD
