Metadata-Version: 2.3
Name: drf-material
Version: 0.3.4
Summary: Material design for Django REST Framework API
License: MIT
Author: Yousef Abu Shanab
Author-email: josephyousef249@gmail.com
Requires-Python: >=3.7
Classifier: License :: OSI Approved :: MIT License
Classifier: Programming Language :: Python :: 3
Classifier: Programming Language :: Python :: 3.7
Classifier: Programming Language :: Python :: 3.8
Classifier: Programming Language :: Python :: 3.9
Classifier: Programming Language :: Python :: 3.10
Classifier: Programming Language :: Python :: 3.11
Classifier: Programming Language :: Python :: 3.12
Classifier: Programming Language :: Python :: 3.13
Requires-Dist: django (>=3.0)
Requires-Dist: djangorestframework (>=3.14)
Project-URL: Homepage, https://github.com/youzarsiph/drf-material/
Project-URL: Repository, https://github.com/youzarsiph/drf-material/
